setup.py
iii/__init__.py
iii/exceptions.py
iii/recnum.py
iii/webpac.py
iii.egg-info/PKG-INFO
iii.egg-info/SOURCES.txt
iii.egg-info/dependency_links.txt
iii.egg-info/requires.txt
iii.egg-info/top_level.txt