Metadata-Version: 1.0
Name: iii
Version: 0.3
Summary: Utilities to work with the Innovative Interfaces, Inc. integrated library system
Home-page: http://bitbucket.org/anarchivist/iii
Author: Mark A. Matienzo
Author-email: mark@matienzo.org
License: GPL
Platform: UNKNOWN
Classifier: Intended Audience :: Education
Classifier: Intended Audience :: Developers
Classifier: Intended Audience :: Information Technology
Classifier: License :: OSI Approved :: GNU General Public License (GPL)
Classifier: Programming Language :: Python
Classifier: Development Status :: 3 - Alpha
